automower_ble/__init__.py
automower_ble/error_codes.py
automower_ble/helpers.py
automower_ble/models.py
automower_ble/mower.py
automower_ble/protocol.json
automower_ble/protocol.py
automower_ble-0.2.8.dist-info/licenses/LICENSE
automower_ble-0.2.8.dist-info/METADATA
automower_ble-0.2.8.dist-info/WHEEL
automower_ble-0.2.8.dist-info/top_level.txt
automower_ble-0.2.8.dist-info/RECORD
