Metadata-Version: 2.4
Name: automower_ble
Version: 0.2.8
Summary: An unofficial reverse engineered Husqvarna Automower Connect BLE library
Author-email: Alistair Francis <alistair@alistair23.me>
Classifier: Environment :: Console
Classifier: Programming Language :: Python :: 3
Classifier: License :: OSI Approved :: MIT License
Requires-Python: >=3.12
License-File: LICENSE
Requires-Dist: bleak
Requires-Dist: bleak_retry_connector
Dynamic: license-file
